{"app":{"bundleName":"com.example.myapplication","debug":false,"versionCode":130200,"versionName":"13.08.8.1001","minAPIVersion":50000012,"targetAPIVersion":60000020,"apiReleaseType":"Release","targetMinorAPIVersion":0,"targetPatchAPIVersion":0,"compileSdkVersion":"6.0.0.47","compileSdkType":"HarmonyOS","appEnvironments":[],"bundleType":"app","buildMode":"release"},"module":{"name":"amap_lbs_map3d","type":"har","deviceTypes":["default","tablet","2in1"],"requestPermissions":[{"name":"ohos.permission.INTERNET"},{"name":"ohos.permission.GET_NETWORK_INFO"}],"packageName":"@amap/amap_lbs_map3d","installationFree":false,"virtualMachine":"ark12.0.2.0","compileMode":"esmodule","dependencies":[]}}
